README
setup.py
SOFHelp/SOFHelp.py
SOFHelp/__init__.py
SOFHelp.egg-info/PKG-INFO
SOFHelp.egg-info/SOURCES.txt
SOFHelp.egg-info/dependency_links.txt
SOFHelp.egg-info/top_level.txt