Metadata-Version: 1.1
Name: SOFHelp
Version: 0.1.1
Summary: StackOverflow help for exception within program which will helpful to debug with proxy support..
Home-page: http://packages.python.org/sofhelp
Author: Arockia Arulnathan
Author-email: arockia.arulnathan@live.in
License: BSD
Keywords: stackoverflow,debug
Platform: UNKNOWN
Classifier: Development Status :: 4 - Beta
Classifier: Topic :: Utilities
Classifier: License :: OSI Approved :: BSD License
